seledroid/__init__.py
seledroid/webdriver/__init__.py
seledroid/webdriver/chrome/webdriver.py
seledroid/webdriver/common/by.py
seledroid/webdriver/common/exception.py
seledroid/webdriver/common/keys.py
seledroid/webdriver/common/utils.py
seledroid/webdriver/remote/command.py
seledroid/webdriver/remote/remote_connection.py
seledroid/webdriver/remote/web_element.py
seledroid/webdriver/support/expected_conditions.py
seledroid/webdriver/support/select.py
seledroid/webdriver/support/wait.py
seledroid-2.0.3.dist-info/METADATA
seledroid-2.0.3.dist-info/WHEEL
seledroid-2.0.3.dist-info/top_level.txt
seledroid-2.0.3.dist-info/RECORD
